akamai_authtoken-0.4.3-py2.7-nspkg.pth
akamai/authtoken/__init__.py
akamai/authtoken/authtoken.py
akamai_authtoken-0.4.3.dist-info/DESCRIPTION.rst
akamai_authtoken-0.4.3.dist-info/METADATA
akamai_authtoken-0.4.3.dist-info/RECORD
akamai_authtoken-0.4.3.dist-info/WHEEL
akamai_authtoken-0.4.3.dist-info/metadata.json
akamai_authtoken-0.4.3.dist-info/namespace_packages.txt
akamai_authtoken-0.4.3.dist-info/top_level.txt
